yandil/__init__.py
yandil/argument.py
yandil/configuration/__init__.py
yandil/configuration/configuration_container.py
yandil/configuration/environment.py
yandil/container.py
yandil/declarative/__init__.py
yandil/declarative/decorators.py
yandil/dependency.py
yandil/dependency_filler.py
yandil/discovery/__init__.py
yandil/discovery/class_discovery.py
yandil/discovery/class_feature_checks.py
yandil/discovery/module_discovery.py
yandil/errors/__init__.py
yandil/errors/abstract_class_not_allowed_error.py
yandil/errors/configuration_value_type_mismatch_error.py
yandil/errors/dependency_not_found_error.py
yandil/errors/instance_and_class_does_not_match_error.py
yandil/errors/missing_configuration_value_error.py
yandil/errors/missing_type_hint_item_type_error.py
yandil/errors/primary_dependency_already_defined_error.py
yandil/errors/primary_dependency_not_found_error.py
yandil/loaders/__init__.py
yandil/loaders/declarative_dependency_loader.py
yandil/loaders/self_discover_dependency_loader.py
yandil/typing_tools.py
yandil-0.4.0.dist-info/LICENSE
yandil-0.4.0.dist-info/METADATA
yandil-0.4.0.dist-info/WHEEL
yandil-0.4.0.dist-info/RECORD
