Metadata-Version: 2.1
Name: yandil
Version: 0.4.0
Summary: Yet ANother Dependency Injection Library
Home-page: https://github.com/DeejayRevok/yandil
License: BSD-3-Clause
Keywords: dependency injection,di
Author: DeejayRevok
Author-email: seryi_one@hotmail.com
Requires-Python: >=3.10.0,<3.11.0
Classifier: License :: OSI Approved :: BSD License
Classifier: Programming Language :: Python :: 3
Classifier: Programming Language :: Python :: 3.10
Project-URL: Repository, https://github.com/DeejayRevok/yandil
